Metadata-Version: 1.1
Name: TPTPr
Version: 0.1
Summary: T. Pelz Test Project - TPTP
Home-page: No URL
Author: T. Pelz
Author-email: tapelz@gmail.com
License: UNKNOWN
Download-URL: Github?
Platform: UNKNOWN
